pyBodyTrack/__init__.py
pyBodyTrack/faceTrack.py
pyBodyTrack/handTrack.py
pyBodyTrack/holisticTrack.py
pyBodyTrack/poseTrack.py
pybodytrack_serotonin-0.0.1.dist-info/LICENSE
pybodytrack_serotonin-0.0.1.dist-info/METADATA
pybodytrack_serotonin-0.0.1.dist-info/WHEEL
pybodytrack_serotonin-0.0.1.dist-info/top_level.txt
pybodytrack_serotonin-0.0.1.dist-info/RECORD
