Metadata-Version: 2.1
Name: pybodytrack-serotonin
Version: 0.0.1
Summary: use tools like hand tracking or body tracking with python
Home-page: https://github.com/serotoninx/pytools/pybodytrack
Author: serotonin
Author-email: ezeq.david0611@gmail.com
License: UNKNOWN
Project-URL: Bug Tracker, https://github.com/pytools/pybodytrack/issues
Platform: UNKNOWN
Classifier: Programming Language :: Python :: 3
Classifier: License :: OSI Approved :: MIT License
Classifier: Operating System :: OS Independent
Requires-Python: >=3.6
License-File: LICENSE
